AUTHORS.rst
CONTRIBUTING.rst
HISTORY.rst
LICENSE
MANIFEST.in
README.rst
setup.cfg
setup.py
docs/Makefile
docs/authors.rst
docs/conf.py
docs/contributing.rst
docs/history.rst
docs/index.rst
docs/installation.rst
docs/make.bat
docs/readme.rst
docs/usage.rst
sample/ms-vscode-remote.remote-ssh.vsix
sample/ms-vscode-remote.vscode-remote-extensionpack-0.21.0.vsix
tests/__init__.py
tests/test_vscode_ssh_extension_alias.py
vscode_ssh_extension_alias/__init__.py
vscode_ssh_extension_alias/vscode_ssh_extension_alias.py
vscode_ssh_extension_alias.egg-info/PKG-INFO
vscode_ssh_extension_alias.egg-info/SOURCES.txt
vscode_ssh_extension_alias.egg-info/dependency_links.txt
vscode_ssh_extension_alias.egg-info/not-zip-safe
vscode_ssh_extension_alias.egg-info/top_level.txt